{
  "tasks": [
    {
      "id": 1,
      "title": "Direct Directives Architect",
      "listId": 3,
      "category": "Technologies",
      "text": "Lorem Ipsum is simply dummy text of the printing and typesetting industry. Lorem Ipsum has been the industry's standard dummy text ever since the 1500s"
    },
    {
      "title": "Direct Directives Architect",
      "listId": 1,
      "category": "Technologies",
      "id": 2,
      "text": "Lorem Ipsum is simply dummy text of the printing and typesetting industry. Lorem Ipsum has been the industry's standard dummy text ever since the 1500s"
    },
    {
      "title": "Chief Directives Representative",
      "listId": 2,
      "category": "Program",
      "id": 3,
      "text": "Lorem Ipsum is simply dummy text of the printing and typesetting industry. Lorem Ipsum has been the industry's standard dummy text ever since the 1500s"
    },
    {
      "title": "Chief Directives Representative",
      "listId": 1,
      "category": "Technologies",
      "id": 5,
      "text": "Lorem Ipsum is simply dummy text of the printing and typesetting industry. Lorem Ipsum has been the industry's standard dummy text ever since the 1500s"
    },
    {
      "title": "New Note",
      "text": "Lorem",
      "category": "CS50",
      "listId": 2,
      "id": 6
    },
    {
      "title": "One more note",
      "text": "lorem",
      "category": "Pyton",
      "listId": 3,
      "id": 7
    },
    {
      "title": "asd",
      "text": "asdasda",
      "category": "Pyton",
      "listId": 1,
      "id": 8
    },
    {
      "title": "",
      "text": "",
      "category": "Program",
      "listId": 2,
      "id": 9
    },
    {
      "title": "sadfa",
      "text": "sadASDASD",
      "category": "asdsadad",
      "listId": 2,
      "id": 10
    }
  ],
  "categories": [
    {
      "id": 0,
      "name": "Technologies",
      "color": "#f55742"
    },
    {
      "id": 1,
      "name": "Design",
      "color": "#f5e342"
    },
    {
      "id": 2,
      "name": "Program",
      "color": "#da42f5"
    },
    {
      "color": "#5ac216",
      "id": 3,
      "name": "Photo"
    },
    {
      "color": "#17d958",
      "id": 4,
      "name": "CS50"
    },
    {
      "color": "#d8bd12",
      "id": 5,
      "name": "Pyton"
    }
  ]
}